dashai_plugin_image_classification_hernan2/__init__.py
dashai_plugin_image_classification_hernan2/dataloader_class_template.py
dashai_plugin_image_classification_hernan2/metric_class_template.py
dashai_plugin_image_classification_hernan2/model_class_template.py
dashai_plugin_image_classification_hernan2/task_class_template.py
dashai_plugin_image_classification_hernan2-1.0.dist-info/METADATA
dashai_plugin_image_classification_hernan2-1.0.dist-info/WHEEL
dashai_plugin_image_classification_hernan2-1.0.dist-info/entry_points.txt
dashai_plugin_image_classification_hernan2-1.0.dist-info/RECORD
